sgkit/__init__.py
sgkit/_version.py
sgkit/accelerate.py
sgkit/cohorts.py
sgkit/display.py
sgkit/display_numba_fns.py
sgkit/distarray.py
sgkit/model.py
sgkit/py.typed
sgkit/testing.py
sgkit/typing.py
sgkit/utils.py
sgkit/variables.py
sgkit/window.py
sgkit/distance/__init__.py
sgkit/distance/api.py
sgkit/distance/metrics.py
sgkit/io/__init__.py
sgkit/io/dataset.py
sgkit/io/utils.py
sgkit/io/bgen/__init__.py
sgkit/io/bgen/bgen_reader.py
sgkit/io/plink/__init__.py
sgkit/io/plink/plink_reader.py
sgkit/io/plink/plink_writer.py
sgkit/stats/__init__.py
sgkit/stats/aggregation.py
sgkit/stats/aggregation_numba_fns.py
sgkit/stats/association.py
sgkit/stats/cohort_numba_fns.py
sgkit/stats/conversion.py
sgkit/stats/conversion_numba_fns.py
sgkit/stats/genedrop.py
sgkit/stats/genedrop_numba_fns.py
sgkit/stats/genee.py
sgkit/stats/genee_momentchi2py.py
sgkit/stats/grm.py
sgkit/stats/hwe.py
sgkit/stats/ibs.py
sgkit/stats/ibs_numba_fns.py
sgkit/stats/ld.py
sgkit/stats/pc_relate.py
sgkit/stats/pca.py
sgkit/stats/pedigree.py
sgkit/stats/pedigree_numba_fns.py
sgkit/stats/popgen.py
sgkit/stats/popgen_numba_fns.py
sgkit/stats/preprocessing.py
sgkit/stats/regenie.py
sgkit/stats/truncated_svd.py
sgkit/stats/utils.py
sgkit-0.10.0.dist-info/licenses/LICENSE
sgkit-0.10.0.dist-info/METADATA
sgkit-0.10.0.dist-info/WHEEL
sgkit-0.10.0.dist-info/top_level.txt
sgkit-0.10.0.dist-info/RECORD
